_libinjection.so
libinjection_wheel-0.1.1.dist-info/WHEEL
libinjection_wheel-0.1.1.dist-info/top_level.txt
libinjection_wheel-0.1.1.dist-info/METADATA
libinjection_wheel-0.1.1.dist-info/RECORD
libinjection/__init__.py
libinjection/sqli_fingerprints.py
libinjection/libinjection.py
